[
{ "_creationTime": 1781435545856.9924, "_id": "z976e9d0xm737y40vrvdzs83e188mfyj", "assists": 1, "cleanSheets": 0, "country": "Brazil", "goals": 0, "notes": "BRA 1-1 MAR 2026-06-13. FOX boxscore key play: 32 Vinicius Junior goal assisted by B. Guimaraes; FOX scores page assist leaders also lists B. Guimaraes BRA 1. Sources: foxsports.com/soccer/fifa-world-cup-men-brazil-vs-morocco-jun-13-2026-game-boxscore-647622; foxsports.com/soccer/fifa-world-cup/scores. Synced 2026-06-14T11:16Z", "playerId": "official:brazil:playmaker:bruno-g", "playerName": "BRUNO G.", "updatedAt": 1781435760000 },
{ "_creationTime": 1781435545856.9922, "_id": "z971174wqfb5tw2r9y58sc96en88nmc8", "assists": 1, "cleanSheets": 0, "country": "Brazil", "goals": 0, "notes": "BRA 1-1 MAR 2026-06-13. FOX boxscore key play: 32 Vinicius Junior goal assisted by B. Guimaraes; FOX scores page assist leaders also lists B. Guimaraes BRA 1. Sources: foxsports.com/soccer/fifa-world-cup-men-brazil-vs-morocco-jun-13-2026-game-boxscore-647622; foxsports.com/soccer/fifa-world-cup/scores. Synced 2026-06-14T11:16Z", "playerId": "official:brazil:star:bruno-g", "playerName": "BRUNO G.", "updatedAt": 1781435760000 },
{ "_creationTime": 1781426503401.428, "_id": "z974rw3tt8h8vrs5w14vtwsgr188magg", "assists": 0, "cleanSheets": 1, "country": "Australia", "goals": 0, "notes": "AUS 2-0 TUR 2026-06-14 clean sheet. FotMob/Ahram lineups list Jordan Bos starting; FOX final confirms 2-0. Sources: fotmob.com/matches/turkiye-vs-australia/1gr3uk; english.ahram.org.eg/NewsContentP/66/570706. Synced 2026-06-14T08:41:40Z", "playerId": "official:australia:wildcard:bos", "playerName": "BOS", "updatedAt": 1781426500802 },
{ "_creationTime": 1781426503401.4277, "_id": "z97055n22fj43t35edhh40m86588n11q", "assists": 0, "cleanSheets": 1, "country": "Australia", "goals": 0, "notes": "AUS 2-0 TUR 2026-06-14 clean sheet. FotMob/Ahram lineups list Jordan Bos starting; FOX final confirms 2-0. Sources: fotmob.com/matches/turkiye-vs-australia/1gr3uk; english.ahram.org.eg/NewsContentP/66/570706. Synced 2026-06-14T08:41:40Z", "playerId": "official:australia:defenderKeeper:bos", "playerName": "BOS", "updatedAt": 1781426500802 },
{ "_creationTime": 1781426503401.4275, "_id": "z972gg0zdcrxp1z255v55x21gd88ncqs", "assists": 0, "cleanSheets": 1, "country": "Australia", "goals": 0, "notes": "AUS 2-0 TUR 2026-06-14 clean sheet. FotMob/Ahram lineups list Jacob Italiano starting; FOX final confirms 2-0. Sources: fotmob.com/matches/turkiye-vs-australia/1gr3uk; english.ahram.org.eg/NewsContentP/66/570706. Synced 2026-06-14T08:41:40Z", "playerId": "official:australia:wildcard:italiano", "playerName": "ITALIANO", "updatedAt": 1781426500802 },
{ "_creationTime": 1781426503401.4272, "_id": "z97cjfa4ndspr23bebdp0r40sh88ngn2", "assists": 0, "cleanSheets": 1, "country": "Australia", "goals": 0, "notes": "AUS 2-0 TUR 2026-06-14 clean sheet. FotMob/Ahram lineups list Jacob Italiano starting; FOX final confirms 2-0. Sources: fotmob.com/matches/turkiye-vs-australia/1gr3uk; english.ahram.org.eg/NewsContentP/66/570706. Synced 2026-06-14T08:41:40Z", "playerId": "official:australia:defenderKeeper:italiano", "playerName": "ITALIANO", "updatedAt": 1781426500802 },
{ "_creationTime": 1781426503401.427, "_id": "z979pzzmrd4ht9tnk3pv9br85s88nwr2", "assists": 0, "cleanSheets": 1, "country": "Australia", "goals": 0, "notes": "AUS 2-0 TUR 2026-06-14 clean sheet. FotMob/Ahram lineups list Circati starting; FOX final confirms 2-0. Sources: fotmob.com/matches/turkiye-vs-australia/1gr3uk; english.ahram.org.eg/NewsContentP/66/570706. Synced 2026-06-14T08:41:40Z", "playerId": "official:australia:wildcard:circati", "playerName": "CIRCATI", "updatedAt": 1781426500802 },
{ "_creationTime": 1781426503401.4268, "_id": "z9793vkt986ms842ejwh07jr4988ndbs", "assists": 0, "cleanSheets": 1, "country": "Australia", "goals": 0, "notes": "AUS 2-0 TUR 2026-06-14 clean sheet. FotMob/Ahram lineups list Circati starting; FOX final confirms 2-0. Sources: fotmob.com/matches/turkiye-vs-australia/1gr3uk; english.ahram.org.eg/NewsContentP/66/570706. Synced 2026-06-14T08:41:40Z", "playerId": "official:australia:defenderKeeper:circati", "playerName": "CIRCATI", "updatedAt": 1781426500802 },
{ "_creationTime": 1781426503401.4265, "_id": "z978p8g67ev3a9545m2dpyazr588mt5a", "assists": 1, "cleanSheets": 0, "country": "Australia", "goals": 0, "notes": "AUS 2-0 TUR 2026-06-14. Guardian match report: Irankunda 27 after assist by Paul Okon-Engstler. Source: theguardian.com/football/2026/jun/14/australia-socceroos-turkey-world-cup-2026-group-d-match-report. Synced 2026-06-14T08:41:40Z", "playerId": "official:australia:playmaker:okon-engstler", "playerName": "OKON-ENGSTLER", "updatedAt": 1781426500802 },
{ "_creationTime": 1781426503401.4263, "_id": "z97ach3p058nqdjey3az6y6qkx88npfe", "assists": 0, "cleanSheets": 0, "country": "Australia", "goals": 1, "notes": "AUS 2-0 TUR 2026-06-14. Guardian/FOX/VAVEL: Connor Metcalfe scored Australia's second at 75; no assist source-backed. Sources: theguardian.com/football/2026/jun/14/australia-socceroos-turkey-world-cup-2026-group-d-match-report; vavel.com/...1263370. Synced 2026-06-14T08:41:40Z", "playerId": "official:australia:playmaker:metcalfe", "playerName": "METCALFE", "updatedAt": 1781426500802 },
{ "_creationTime": 1781426503401.426, "_id": "z97cnzxkppdh2h0jm695s2jvg188mjcd", "assists": 0, "cleanSheets": 0, "country": "Australia", "goals": 1, "notes": "AUS 2-0 TUR 2026-06-14. Guardian/FOX/VAVEL: Connor Metcalfe scored Australia's second at 75; no assist source-backed. Sources: theguardian.com/football/2026/jun/14/australia-socceroos-turkey-world-cup-2026-group-d-match-report; vavel.com/...1263370. Synced 2026-06-14T08:41:40Z", "playerId": "official:australia:star:metcalfe", "playerName": "METCALFE", "updatedAt": 1781426500802 },
{ "_creationTime": 1781426503401.4258, "_id": "z97eyy6h88w5y09xbjp0kq03fx88nr1f", "assists": 0, "cleanSheets": 0, "country": "Australia", "goals": 1, "notes": "AUS 2-0 TUR 2026-06-14. Guardian/FOX: Nestory Irankunda scored 27; Guardian credits Paul Okon-Engstler assist. Sources: theguardian.com/football/2026/jun/14/australia-socceroos-turkey-world-cup-2026-group-d-match-report; foxsports.com/...647620. Synced 2026-06-14T08:41:40Z", "playerId": "official:australia:goalGetter:irankunda", "playerName": "IRANKUNDA", "updatedAt": 1781426500802 },
{ "_creationTime": 1781410265275.374, "_id": "z97d5dysk9563bvrfedt4143zd88magr", "assists": 0, "cleanSheets": 1, "country": "Scotland", "goals": 0, "notes": "HAI 0-1 SCO 2026-06-13. FOX final score/lineup show Scotland clean sheet; starters Gunn, Hickey, Hanley, Robertson. Source: foxsports.com/soccer/fifa-world-cup-men-haiti-vs-scotland-jun-13-2026-game-boxscore-647623. Synced 2026-06-14T04:20Z", "playerId": "official:scotland:wildcard:hanley", "playerName": "HANLEY", "updatedAt": 1781410262699 },
{ "_creationTime": 1781410265275.3738, "_id": "z977p1dpdnvxrtm3g2q8t8zvdx88mk93", "assists": 0, "cleanSheets": 1, "country": "Scotland", "goals": 0, "notes": "HAI 0-1 SCO 2026-06-13. FOX final score/lineup show Scotland clean sheet; starters Gunn, Hickey, Hanley, Robertson. Source: foxsports.com/soccer/fifa-world-cup-men-haiti-vs-scotland-jun-13-2026-game-boxscore-647623. Synced 2026-06-14T04:20Z", "playerId": "official:scotland:defenderKeeper:hanley", "playerName": "HANLEY", "updatedAt": 1781410262699 },
{ "_creationTime": 1781410265275.3735, "_id": "z97eme5j6wjzqdbvmr4mqv7ff588njss", "assists": 0, "cleanSheets": 1, "country": "Scotland", "goals": 0, "notes": "HAI 0-1 SCO 2026-06-13. FOX final score/lineup show Scotland clean sheet; starters Gunn, Hickey, Hanley, Robertson. Source: foxsports.com/soccer/fifa-world-cup-men-haiti-vs-scotland-jun-13-2026-game-boxscore-647623. Synced 2026-06-14T04:20Z", "playerId": "official:scotland:wildcard:robertson", "playerName": "ROBERTSON", "updatedAt": 1781410262699 },
{ "_creationTime": 1781410265275.3733, "_id": "z975q1p2t31htnbjbxvng5pdn188nx9w", "assists": 0, "cleanSheets": 1, "country": "Scotland", "goals": 0, "notes": "HAI 0-1 SCO 2026-06-13. FOX final score/lineup show Scotland clean sheet; starters Gunn, Hickey, Hanley, Robertson. Source: foxsports.com/soccer/fifa-world-cup-men-haiti-vs-scotland-jun-13-2026-game-boxscore-647623. Synced 2026-06-14T04:20Z", "playerId": "official:scotland:defenderKeeper:robertson", "playerName": "ROBERTSON", "updatedAt": 1781410262699 },
{ "_creationTime": 1781410265275.373, "_id": "z97c8avyyxn1d5nf1h3sh5sv3588m88r", "assists": 0, "cleanSheets": 1, "country": "Scotland", "goals": 0, "notes": "HAI 0-1 SCO 2026-06-13. FOX final score/lineup show Scotland clean sheet; starters Gunn, Hickey, Hanley, Robertson. Source: foxsports.com/soccer/fifa-world-cup-men-haiti-vs-scotland-jun-13-2026-game-boxscore-647623. Synced 2026-06-14T04:20Z", "playerId": "official:scotland:wildcard:hickey", "playerName": "HICKEY", "updatedAt": 1781410262699 },
{ "_creationTime": 1781410265275.3728, "_id": "z9746fkh9b0v0n79dz9r5v17th88ndy0", "assists": 0, "cleanSheets": 1, "country": "Scotland", "goals": 0, "notes": "HAI 0-1 SCO 2026-06-13. FOX final score/lineup show Scotland clean sheet; starters Gunn, Hickey, Hanley, Robertson. Source: foxsports.com/soccer/fifa-world-cup-men-haiti-vs-scotland-jun-13-2026-game-boxscore-647623. Synced 2026-06-14T04:20Z", "playerId": "official:scotland:defenderKeeper:hickey", "playerName": "HICKEY", "updatedAt": 1781410262699 },
{ "_creationTime": 1781410265275.3726, "_id": "z97dzz43vpa172pypyhrhc0wnd88nh9m", "assists": 0, "cleanSheets": 1, "country": "Scotland", "goals": 0, "notes": "HAI 0-1 SCO 2026-06-13. FOX final score/lineup show Scotland clean sheet; starters Gunn, Hickey, Hanley, Robertson. Source: foxsports.com/soccer/fifa-world-cup-men-haiti-vs-scotland-jun-13-2026-game-boxscore-647623. Synced 2026-06-14T04:20Z", "playerId": "official:scotland:wildcard:gunn", "playerName": "GUNN", "updatedAt": 1781410262699 },
{ "_creationTime": 1781410265275.3723, "_id": "z973k3zmjf7dgxrggsma8atdh188mc2n", "assists": 0, "cleanSheets": 1, "country": "Scotland", "goals": 0, "notes": "HAI 0-1 SCO 2026-06-13. FOX final score/lineup show Scotland clean sheet; starters Gunn, Hickey, Hanley, Robertson. Source: foxsports.com/soccer/fifa-world-cup-men-haiti-vs-scotland-jun-13-2026-game-boxscore-647623. Synced 2026-06-14T04:20Z", "playerId": "official:scotland:defenderKeeper:gunn", "playerName": "GUNN", "updatedAt": 1781410262699 },
{ "_creationTime": 1781410265275.372, "_id": "z972b12vp76jy9jqq8mbdnwyt988mbv8", "assists": 0, "cleanSheets": 0, "country": "Scotland", "goals": 1, "notes": "HAI 0-1 SCO 2026-06-13. FOX: John McGinn scored 28; no assist listed. Guardian calls it a deflected McGinn strike. Sources: foxsports.com/soccer/fifa-world-cup-men-haiti-vs-scotland-jun-13-2026-game-boxscore-647623; Guardian match report. Synced 2026-06-14T04:20Z", "playerId": "official:scotland:playmaker:mcginn", "playerName": "MCGINN", "updatedAt": 1781410262699 },
{ "_creationTime": 1781410265275.3718, "_id": "z97bcv62fedjkegcn1z887vfth88m5yf", "assists": 0, "cleanSheets": 0, "country": "Scotland", "goals": 1, "notes": "HAI 0-1 SCO 2026-06-13. FOX: John McGinn scored 28; no assist listed. Guardian calls it a deflected McGinn strike. Sources: foxsports.com/soccer/fifa-world-cup-men-haiti-vs-scotland-jun-13-2026-game-boxscore-647623; Guardian match report. Synced 2026-06-14T04:20Z", "playerId": "official:scotland:star:mcginn", "playerName": "MCGINN", "updatedAt": 1781410262699 },
{ "_creationTime": 1781410265275.3716, "_id": "z97d39ex12k6py8mnpfkhn5g1d88mbga", "assists": 0, "cleanSheets": 0, "country": "Switzerland", "goals": 1, "notes": "QAT 1-1 SUI 2026-06-13. FOX/Guardian: Breel Embolo penalty 17; Boualem Khoukhi 90+4/90+5 header from Homan Ahmed cross. Sources: foxsports.com/soccer/fifa-world-cup-men-qatar-vs-switzerland-jun-13-2026-game-boxscore-647621; Guardian live. Synced 2026-06-14T04:20Z", "playerId": "official:switzerland:goalGetter:embolo", "playerName": "EMBOLO", "updatedAt": 1781410262699 },
{ "_creationTime": 1781410265275.3713, "_id": "z972yckn4vemnjq0k2ddvxzry988nqrs", "assists": 0, "cleanSheets": 0, "country": "Switzerland", "goals": 1, "notes": "QAT 1-1 SUI 2026-06-13. FOX/Guardian: Breel Embolo penalty 17; Boualem Khoukhi 90+4/90+5 header from Homan Ahmed cross. Sources: foxsports.com/soccer/fifa-world-cup-men-qatar-vs-switzerland-jun-13-2026-game-boxscore-647621; Guardian live. Synced 2026-06-14T04:20Z", "playerId": "official:switzerland:star:embolo", "playerName": "EMBOLO", "updatedAt": 1781410262699 },
{ "_creationTime": 1781410265275.371, "_id": "z9710b25mztce87a07w8045er988m22p", "assists": 0, "cleanSheets": 0, "country": "Morocco", "goals": 1, "notes": "BRA 1-1 MAR 2026-06-13. FOX/Guardian: Ismael Saibari scored 21; Vinicius Junior scored 32. Sources: foxsports.com/live-blog/soccer/brazil-vs-morocco-live-updates-score-top-plays-from-todays-action; theguardian.com/football/live/2026/jun/13/brazil-v-morocco-world-cup-2026-live. Synced 2026-06-14T04:2", "playerId": "official:morocco:playmaker:saibari", "playerName": "SAIBARI", "updatedAt": 1781410262699 },
{ "_creationTime": 1781410265275.3708, "_id": "z9711eaj20y3ws8zv676p9b6fs88m9m9", "assists": 0, "cleanSheets": 0, "country": "Brazil", "goals": 1, "notes": "BRA 1-1 MAR 2026-06-13. FOX/ESPN: Vinicius Junior scored 32; Saibari 21. Sources: foxsports.com/soccer/fifa-world-cup-men-brazil-vs-morocco-jun-13-2026-game-boxscore-647622; espn.com/soccer/match/_/gameId/760419. Synced 2026-06-14T04:20Z", "playerId": "official:brazil:goalGetter:vini-jr", "playerName": "VINI JR.", "updatedAt": 1781410262699 },
{ "_creationTime": 1781410265275.3706, "_id": "z97dcs9hymvpxxg7pfm8ssk3c188nxf1", "assists": 0, "cleanSheets": 0, "country": "Brazil", "goals": 1, "notes": "BRA 1-1 MAR 2026-06-13. FOX/ESPN: Vinicius Junior scored 32; Saibari 21. Sources: foxsports.com/soccer/fifa-world-cup-men-brazil-vs-morocco-jun-13-2026-game-boxscore-647622; espn.com/soccer/match/_/gameId/760419. Synced 2026-06-14T04:20Z", "playerId": "official:brazil:star:vini-jr", "playerName": "VINI JR.", "updatedAt": 1781410262699 },
{ "_creationTime": 1781410265275.3704, "_id": "z97dvx0mqk6ydvq12jzw98sb9s88ny4n", "assists": 0, "cleanSheets": 0, "country": "Brazil", "goals": 1, "notes": "BRA 1-1 MAR 2026-06-13. FOX/ESPN: Vinicius Junior scored 32; Saibari 21. Sources: foxsports.com/soccer/fifa-world-cup-men-brazil-vs-morocco-jun-13-2026-game-boxscore-647622; espn.com/soccer/match/_/gameId/760419. Synced 2026-06-14T04:20Z", "playerId": "vinicius", "playerName": "Vinicius Junior", "updatedAt": 1781410262699 },
{ "_creationTime": 1781410265275.37, "_id": "z97df18j2jmsmze2128nwdkm8988m2bm", "assists": 1, "cleanSheets": 0, "country": "Bosnia and Herzegovina", "goals": 0, "notes": "CAN 1-1 BIH 2026-06-12. AP: Lukic 21 after Sead Kolasinac flicked header from Ivan Basic corner; no clean sheet. Source: https://apnews.com/article/c58d5a51d827dd0456fe56e65eca1518 Synced 2026-06-12T21:40Z", "playerId": "official:bosnia-and-herzegovina:defenderKeeper:kolasinac", "playerName": "KOLASINAC", "updatedAt": 1781300468357 },
{ "_creationTime": 1781410265275.3699, "_id": "z976yk03msy69c10rd3wgmm9v988nf89", "assists": 1, "cleanSheets": 0, "country": "Bosnia and Herzegovina", "goals": 0, "notes": "CAN 1-1 BIH 2026-06-12. AP: Lukic 21 after Sead Kolasinac flicked header from Ivan Basic corner; no clean sheet. Source: https://apnews.com/article/c58d5a51d827dd0456fe56e65eca1518 Synced 2026-06-12T21:40Z", "playerId": "official:bosnia-and-herzegovina:wildcard:kolasinac", "playerName": "KOLASINAC", "updatedAt": 1781300468357 },
{ "_creationTime": 1781410265275.3696, "_id": "z9743wzh4kh9gxmemnaapvvcxn88mn8d", "assists": 0, "cleanSheets": 0, "country": "Canada", "goals": 1, "notes": "CAN 1-1 BIH 2026-06-12. AP: Larin scored 78 from Promise David pass; Guardian confirms FT 1-1. Sources: https://apnews.com/article/c58d5a51d827dd0456fe56e65eca1518 https://www.theguardian.com/football/live/2026/jun/12/canada-v-bosnia-and-herzegovina-world-cup-2026-live Synced 2026-06-12T21:40Z", "playerId": "official:canada:goalGetter:larin", "playerName": "LARIN", "updatedAt": 1781300468357 },
{ "_creationTime": 1781410265275.3694, "_id": "z9759zdk696fzhkc8yg6aeq8ph88nxsm", "assists": 1, "cleanSheets": 0, "country": "Canada", "goals": 0, "notes": "CAN 1-1 BIH 2026-06-12. AP: Larin converted Promise David pass; Guardian notes Promise flick led to Larin. Sources: https://apnews.com/article/c58d5a51d827dd0456fe56e65eca1518 https://www.theguardian.com/football/live/2026/jun/12/canada-v-bosnia-and-herzegovina-world-cup-2026-live Synced 2026-06-12T21:40Z", "playerId": "official:canada:goalGetter:promise", "playerName": "PROMISE", "updatedAt": 1781300468357 },
{ "_creationTime": 1781410265275.3691, "_id": "z976enqmhqrzzsf8ttftsn5ytn88n9fe", "assists": 0, "cleanSheets": 0, "country": "Canada", "goals": 1, "notes": "CAN 1-1 BIH 2026-06-12. AP: Larin scored 78 from Promise David pass; Guardian confirms FT 1-1. Sources: https://apnews.com/article/c58d5a51d827dd0456fe56e65eca1518 https://www.theguardian.com/football/live/2026/jun/12/canada-v-bosnia-and-herzegovina-world-cup-2026-live Synced 2026-06-12T21:40Z", "playerId": "official:canada:star:larin", "playerName": "LARIN", "updatedAt": 1781300468357 },
{ "_creationTime": 1781410265275.369, "_id": "z97b6zwvrhwtgc6jqnt5m8nz2x88mp9w", "assists": 1, "cleanSheets": 0, "country": "Czechia", "goals": 0, "notes": "South Korea 2-1 Czechia, 2026-06-12 UTC. Vladimir Coufal assisted Ladislav Krejci 59; Czechia conceded twice, no clean sheet. Sources: ESPN https://www.espn.com/soccer/match/_/gameId/760414; FOX https://www.foxsports.com/soccer/fifa-world-cup-men-south-korea-vs-czechia-jun-11-2026-game-boxscore-647617. Synced 2026-06-12T04:07Z", "playerId": "official:czechia:defenderKeeper:coufal", "playerName": "COUFAL", "updatedAt": 1781237220000 },
{ "_creationTime": 1781410265275.3687, "_id": "z9740j1e23x043cztwdpzds1m188mtb5", "assists": 1, "cleanSheets": 0, "country": "Czechia", "goals": 0, "notes": "South Korea 2-1 Czechia, 2026-06-12 UTC. Vladimir Coufal assisted Ladislav Krejci 59; Czechia conceded twice, no clean sheet. Sources: ESPN https://www.espn.com/soccer/match/_/gameId/760414; FOX https://www.foxsports.com/soccer/fifa-world-cup-men-south-korea-vs-czechia-jun-11-2026-game-boxscore-647617. Synced 2026-06-12T04:07Z", "playerId": "official:czechia:wildcard:coufal", "playerName": "COUFAL", "updatedAt": 1781237220000 },
{ "_creationTime": 1781410265275.3684, "_id": "z97fretvkx2xvwypfm53gbmt5x88nx26", "assists": 0, "cleanSheets": 1, "country": "Mexico", "goals": 0, "notes": "Mexico clean sheet in 2-0 vs South Africa, 2026-06-11; Montes started and was sent off at 90+3 after clean sheet stood. Sources: FIFA match centre, Guardian live, ESPN lineup snippet. Synced 2026-06-11T22:04Z", "playerId": "official:mexico:defenderKeeper:c-montes", "playerName": "C. MONTES", "updatedAt": 1781215473000 },
{ "_creationTime": 1781410265275.3682, "_id": "z9759e14p9pmnpb8sry0fpd0fn88m0ym", "assists": 0, "cleanSheets": 1, "country": "Mexico", "goals": 0, "notes": "Mexico clean sheet in 2-0 vs South Africa, 2026-06-11; Sanchez listed in starting back line. Sources: FIFA match centre, Guardian live, ESPN lineup snippet. Synced 2026-06-11T22:04Z", "playerId": "official:mexico:defenderKeeper:j-s-nchez", "playerName": "J. SÁNCHEZ", "updatedAt": 1781215473000 },
{ "_creationTime": 1781410265275.368, "_id": "z9737kczy61mgrbr92xkyqycs188n2w6", "assists": 0, "cleanSheets": 1, "country": "Mexico", "goals": 0, "notes": "Mexico clean sheet in 2-0 vs South Africa, 2026-06-11; Vasquez listed in starting back line. Sources: FIFA match centre, Guardian live, ESPN lineup snippet. Synced 2026-06-11T22:04Z", "playerId": "official:mexico:defenderKeeper:j-v-squez", "playerName": "J. VÁSQUEZ", "updatedAt": 1781215473000 },
{ "_creationTime": 1781410265275.3677, "_id": "z97f0gk485x64f07vmt50b6e2d88n1mn", "assists": 0, "cleanSheets": 1, "country": "Mexico", "goals": 0, "notes": "Mexico clean sheet in 2-0 vs South Africa, 2026-06-11; Rangel listed as starting GK. Sources: FIFA match centre, Guardian live, ESPN lineup snippet. Synced 2026-06-11T22:04Z", "playerId": "official:mexico:defenderKeeper:r-rangel", "playerName": "R. RANGEL", "updatedAt": 1781215473000 },
{ "_creationTime": 1781410265275.3674, "_id": "z9794x4aen4602r3staj25zxsh88mgbj", "assists": 0, "cleanSheets": 0, "country": "Mexico", "goals": 1, "notes": "Mexico 2-0 South Africa, 2026-06-11. Sources: FIFA match centre https://www.fifa.com/en/match-centre/match/17/285023/289273/400021443; Guardian live; SportingNews live. Synced 2026-06-11T22:04Z", "playerId": "official:mexico:goalGetter:j-qui-ones", "playerName": "J. QUIÑONES", "updatedAt": 1781215473000 },
{ "_creationTime": 1781410265275.3672, "_id": "z976ewmczdg3tznxqvyacte3vn88ngw9", "assists": 0, "cleanSheets": 0, "country": "Mexico", "goals": 1, "notes": "Mexico 2-0 South Africa, 2026-06-11. Sources: FIFA match centre https://www.fifa.com/en/match-centre/match/17/285023/289273/400021443; Guardian live; SportingNews live. Synced 2026-06-11T22:04Z", "playerId": "official:mexico:goalGetter:ra-l", "playerName": "RAÚL", "updatedAt": 1781215473000 },
{ "_creationTime": 1781410265275.367, "_id": "z970c0hhs26axtngx5qtf163vx88m70p", "assists": 1, "cleanSheets": 0, "country": "Mexico", "goals": 0, "notes": "MEX 2-0 RSA 2026-06-11. FOX: 9 J. Quinones goal assisted by E. Lira; ESPN team stats: MEX 2 assists; FIFA report confirms result. Sources: foxsports.com/soccer/fifa-world-cup-men-mexico-vs-south-africa-jun-11-2026-game-boxscore-647616 Synced 2026-06-12T04:37Z", "playerId": "official:mexico:playmaker:e-lira", "playerName": "E. LIRA", "updatedAt": 1781239020000 },
{ "_creationTime": 1781410265275.3667, "_id": "z9745756ys5mds5cdc61kg6b8s88m7hw", "assists": 1, "cleanSheets": 0, "country": "Mexico", "goals": 0, "notes": "MEX 2-0 RSA 2026-06-11. FOX: 9 J. Quinones goal assisted by E. Lira; ESPN team stats: MEX 2 assists; FIFA report confirms result. Sources: foxsports.com/soccer/fifa-world-cup-men-mexico-vs-south-africa-jun-11-2026-game-boxscore-647616 Synced 2026-06-12T04:37Z", "playerId": "official:mexico:star:e-lira", "playerName": "E. LIRA", "updatedAt": 1781239020000 },
{ "_creationTime": 1781410265275.3665, "_id": "z972rx4gx98m3gpwys1xnkzbj988njsf", "assists": 0, "cleanSheets": 0, "country": "Mexico", "goals": 1, "notes": "Mexico 2-0 South Africa, 2026-06-11. Sources: FIFA match centre https://www.fifa.com/en/match-centre/match/17/285023/289273/400021443; Guardian live; SportingNews live. Synced 2026-06-11T22:04Z", "playerId": "official:mexico:star:ra-l", "playerName": "RAÚL", "updatedAt": 1781215473000 },
{ "_creationTime": 1781410265275.3662, "_id": "z97fcwgsp1j5c1vr32che4jphx88mjr0", "assists": 0, "cleanSheets": 1, "country": "Mexico", "goals": 0, "notes": "Mexico clean sheet in 2-0 vs South Africa, 2026-06-11; Montes started and was sent off at 90+3 after clean sheet stood. Sources: FIFA match centre, Guardian live, ESPN lineup snippet. Synced 2026-06-11T22:04Z", "playerId": "official:mexico:wildcard:c-montes", "playerName": "C. MONTES", "updatedAt": 1781215473000 },
{ "_creationTime": 1781410265275.366, "_id": "z975sjz6jtgacc1tsgyc9x6g3s88m8t9", "assists": 1, "cleanSheets": 0, "country": "Mexico", "goals": 0, "notes": "MEX 2-0 RSA 2026-06-11. FOX: 9 J. Quinones goal assisted by E. Lira; ESPN team stats: MEX 2 assists; FIFA report confirms result. Sources: foxsports.com/soccer/fifa-world-cup-men-mexico-vs-south-africa-jun-11-2026-game-boxscore-647616 Synced 2026-06-12T04:37Z", "playerId": "official:mexico:wildcard:e-lira", "playerName": "E. LIRA", "updatedAt": 1781239020000 },
{ "_creationTime": 1781410265275.3657, "_id": "z97d1kqncpqz4kqpfcpaqh9b6n88mxg3", "assists": 0, "cleanSheets": 1, "country": "Mexico", "goals": 0, "notes": "Mexico clean sheet in 2-0 vs South Africa, 2026-06-11; Sanchez listed in starting back line. Sources: FIFA match centre, Guardian live, ESPN lineup snippet. Synced 2026-06-11T22:04Z", "playerId": "official:mexico:wildcard:j-s-nchez", "playerName": "J. SÁNCHEZ", "updatedAt": 1781215473000 },
{ "_creationTime": 1781410265275.3655, "_id": "z978y67teg136ste6ex0jt4wv588nx68", "assists": 0, "cleanSheets": 1, "country": "Mexico", "goals": 0, "notes": "Mexico clean sheet in 2-0 vs South Africa, 2026-06-11; Vasquez listed in starting back line. Sources: FIFA match centre, Guardian live, ESPN lineup snippet. Synced 2026-06-11T22:04Z", "playerId": "official:mexico:wildcard:j-v-squez", "playerName": "J. VÁSQUEZ", "updatedAt": 1781215473000 },
{ "_creationTime": 1781410265275.3652, "_id": "z97d1bzw8h6xvmc50df1prfttx88m3zs", "assists": 0, "cleanSheets": 1, "country": "Mexico", "goals": 0, "notes": "Mexico clean sheet in 2-0 vs South Africa, 2026-06-11; Rangel listed as starting GK. Sources: FIFA match centre, Guardian live, ESPN lineup snippet. Synced 2026-06-11T22:04Z", "playerId": "official:mexico:wildcard:r-rangel", "playerName": "R. RANGEL", "updatedAt": 1781215473000 },
{ "_creationTime": 1781410265275.365, "_id": "z9792wa6ddnkxj4s49f54ns8h988nehw", "assists": 0, "cleanSheets": 0, "country": "South Korea", "goals": 1, "notes": "South Korea 2-1 Czechia, 2026-06-12 UTC. Oh Hyeon-gyu scored 80, assisted by Hwang In-beom. Sources: ESPN https://www.espn.com/soccer/match/_/gameId/760414; FOX https://www.foxsports.com/soccer/fifa-world-cup-men-south-korea-vs-czechia-jun-11-2026-game-boxscore-647617. Synced 2026-06-12T04:07Z", "playerId": "official:south-korea:goalGetter:hyeongyu", "playerName": "HYEONGYU", "updatedAt": 1781237220000 },
{ "_creationTime": 1781410265275.3647, "_id": "z9717dr1wjrvgf4f932c4kfg7s88mkhd", "assists": 1, "cleanSheets": 0, "country": "South Korea", "goals": 1, "notes": "South Korea 2-1 Czechia, 2026-06-12 UTC. Hwang In-beom scored 67 and assisted Oh Hyeon-gyu 80. Sources: ESPN https://www.espn.com/soccer/match/_/gameId/760414; FOX https://www.foxsports.com/soccer/fifa-world-cup-men-south-korea-vs-czechia-jun-11-2026-game-boxscore-647617. Synced 2026-06-12T04:07Z", "playerId": "official:south-korea:playmaker:inbeom", "playerName": "INBEOM", "updatedAt": 1781237220000 },
{ "_creationTime": 1781410265275.3645, "_id": "z976qfwh7njvav30wpm5jw6n5588mn64", "assists": 1, "cleanSheets": 0, "country": "South Korea", "goals": 1, "notes": "South Korea 2-1 Czechia, 2026-06-12 UTC. Hwang In-beom scored 67 and assisted Oh Hyeon-gyu 80. Sources: ESPN https://www.espn.com/soccer/match/_/gameId/760414; FOX https://www.foxsports.com/soccer/fifa-world-cup-men-south-korea-vs-czechia-jun-11-2026-game-boxscore-647617. Synced 2026-06-12T04:07Z", "playerId": "official:south-korea:star:inbeom", "playerName": "INBEOM", "updatedAt": 1781237220000 },
{ "_creationTime": 1781410265275.3643, "_id": "z973rth8trmjf8txm9kgzf0ets88nkpd", "assists": 1, "cleanSheets": 0, "country": "South Korea", "goals": 1, "notes": "South Korea 2-1 Czechia, 2026-06-12 UTC. Hwang In-beom scored 67 and assisted Oh Hyeon-gyu 80. Sources: ESPN https://www.espn.com/soccer/match/_/gameId/760414; FOX https://www.foxsports.com/soccer/fifa-world-cup-men-south-korea-vs-czechia-jun-11-2026-game-boxscore-647617. Synced 2026-06-12T04:07Z", "playerId": "official:south-korea:wildcard:inbeom", "playerName": "INBEOM", "updatedAt": 1781237220000 },
{ "_creationTime": 1781410265275.364, "_id": "z9744dwz744askq2sfc3j8vt9d88n6xc", "assists": 0, "cleanSheets": 0, "country": "United States", "goals": 2, "notes": "USA 4-1 PAR 2026-06-12. FOX boxscore: Balogun 31 assist Pulisic, 45+5 assist Tillman; ESPN: Reyna 90+7 assist Freeman; AP/Guardian confirm result. Synced 2026-06-13T05:37Z", "playerId": "official:united-states:goalGetter:balogun", "playerName": "BALOGUN", "updatedAt": 1781329229032 },
{ "_creationTime": 1781410265275.3638, "_id": "z97fr57dd8pr2zp1gphxse18c188nen9", "assists": 1, "cleanSheets": 0, "country": "United States", "goals": 0, "notes": "USA 4-1 PAR 2026-06-12. FOX boxscore: Balogun 31 assist Pulisic, 45+5 assist Tillman; ESPN: Reyna 90+7 assist Freeman; AP/Guardian confirm result. Synced 2026-06-13T05:37Z", "playerId": "official:united-states:goalGetter:pulisic", "playerName": "PULISIC", "updatedAt": 1781329229032 },
{ "_creationTime": 1781410265275.3635, "_id": "z97366xhfb3va4zhdtte0dtgqd88mqr3", "assists": 0, "cleanSheets": 0, "country": "United States", "goals": 1, "notes": "USA 4-1 PAR 2026-06-12. FOX boxscore: Balogun 31 assist Pulisic, 45+5 assist Tillman; ESPN: Reyna 90+7 assist Freeman; AP/Guardian confirm result. Synced 2026-06-13T05:37Z", "playerId": "official:united-states:playmaker:reyna", "playerName": "REYNA", "updatedAt": 1781329229032 },
{ "_creationTime": 1781410265275.3633, "_id": "z9775j6ns9jrch4k9z7t84f0xd88mpwc", "assists": 1, "cleanSheets": 0, "country": "United States", "goals": 0, "notes": "USA 4-1 PAR 2026-06-12. FOX boxscore: Balogun 31 assist Pulisic, 45+5 assist Tillman; ESPN: Reyna 90+7 assist Freeman; AP/Guardian confirm result. Synced 2026-06-13T05:37Z", "playerId": "official:united-states:playmaker:tillman", "playerName": "TILLMAN", "updatedAt": 1781329229032 },
{ "_creationTime": 1781410265275.363, "_id": "z97fgd3v6swjbcgndf76essd4d88nev8", "assists": 1, "cleanSheets": 0, "country": "United States", "goals": 0, "notes": "USA 4-1 PAR 2026-06-12. FOX boxscore: Balogun 31 assist Pulisic, 45+5 assist Tillman; ESPN: Reyna 90+7 assist Freeman; AP/Guardian confirm result. Synced 2026-06-13T05:37Z", "playerId": "official:united-states:star:pulisic", "playerName": "PULISIC", "updatedAt": 1781329229032 },
{ "_creationTime": 1781410265275.3628, "_id": "z97335qt5r60s09rzt1y646c8d88msfy", "assists": 0, "cleanSheets": 0, "country": "United States", "goals": 1, "notes": "USA 4-1 PAR 2026-06-12. FOX boxscore: Balogun 31 assist Pulisic, 45+5 assist Tillman; ESPN: Reyna 90+7 assist Freeman; AP/Guardian confirm result. Synced 2026-06-13T05:37Z", "playerId": "official:united-states:star:reyna", "playerName": "REYNA", "updatedAt": 1781329229032 },
{ "_creationTime": 1781410265275.3625, "_id": "z971s20r2cxad45xfnk1ncj12988m80c", "assists": 1, "cleanSheets": 0, "country": "United States", "goals": 0, "notes": "USA 4-1 PAR 2026-06-12. FOX boxscore: Balogun 31 assist Pulisic, 45+5 assist Tillman; ESPN: Reyna 90+7 assist Freeman; AP/Guardian confirm result. Synced 2026-06-13T05:37Z", "playerId": "pulisic", "playerName": "Christian Pulisic", "updatedAt": 1781329229032 }
]
